sf2utils/__init__.py
sf2utils/bag.py
sf2utils/generator.py
sf2utils/instrument.py
sf2utils/modulator.py
sf2utils/preset.py
sf2utils/riffparser.py
sf2utils/sample.py
sf2utils/sf2parse.py
sf2utils/tests/__init__.py
sf2utils/tests/test_parse.py
sf2utils-0.9.0.dist-info/DESCRIPTION.rst
sf2utils-0.9.0.dist-info/METADATA
sf2utils-0.9.0.dist-info/RECORD
sf2utils-0.9.0.dist-info/WHEEL
sf2utils-0.9.0.dist-info/entry_points.txt
sf2utils-0.9.0.dist-info/metadata.json
sf2utils-0.9.0.dist-info/pbr.json
sf2utils-0.9.0.dist-info/top_level.txt
